jinja_to_js/__init__.py
jinja_to_js/__main__.py
jinja_to_js-3.2.3.dist-info/METADATA
jinja_to_js-3.2.3.dist-info/RECORD
jinja_to_js-3.2.3.dist-info/WHEEL
jinja_to_js-3.2.3.dist-info/entry_points.txt
jinja_to_js-3.2.3.dist-info/top_level.txt
